pmrlanms-1.8.data/purelib/lanms/__init__.py
pmrlanms-1.8.data/purelib/lanms/adaptor.so
pmrlanms-1.8.dist-info/LICENSE
pmrlanms-1.8.dist-info/METADATA
pmrlanms-1.8.dist-info/WHEEL
pmrlanms-1.8.dist-info/top_level.txt
pmrlanms-1.8.dist-info/RECORD
